azure/mgmt/durabletask/__init__.py
azure/mgmt/durabletask/_client.py
azure/mgmt/durabletask/_configuration.py
azure/mgmt/durabletask/_model_base.py
azure/mgmt/durabletask/_patch.py
azure/mgmt/durabletask/_serialization.py
azure/mgmt/durabletask/_validation.py
azure/mgmt/durabletask/_version.py
azure/mgmt/durabletask/py.typed
azure/mgmt/durabletask/_utils/__init__.py
azure/mgmt/durabletask/_utils/model_base.py
azure/mgmt/durabletask/_utils/serialization.py
azure/mgmt/durabletask/aio/__init__.py
azure/mgmt/durabletask/aio/_client.py
azure/mgmt/durabletask/aio/_configuration.py
azure/mgmt/durabletask/aio/_patch.py
azure/mgmt/durabletask/aio/operations/__init__.py
azure/mgmt/durabletask/aio/operations/_operations.py
azure/mgmt/durabletask/aio/operations/_patch.py
azure/mgmt/durabletask/models/__init__.py
azure/mgmt/durabletask/models/_enums.py
azure/mgmt/durabletask/models/_models.py
azure/mgmt/durabletask/models/_patch.py
azure/mgmt/durabletask/operations/__init__.py
azure/mgmt/durabletask/operations/_operations.py
azure/mgmt/durabletask/operations/_patch.py
azure_mgmt_durabletask-1.0.0.dist-info/licenses/LICENSE
azure_mgmt_durabletask-1.0.0.dist-info/METADATA
azure_mgmt_durabletask-1.0.0.dist-info/WHEEL
azure_mgmt_durabletask-1.0.0.dist-info/top_level.txt
azure_mgmt_durabletask-1.0.0.dist-info/RECORD
